{
  "title": "The Power of HABIT",
  "image": "https://images-na.ssl-images-amazon.com/images/I/51ejXdSceNL._AA300_.jpg",
  "category": "book",
  "description": "The Power of HABIT: Why We Do What We Do in Life and Business. A young woman walks into a laboratory. Over the past two years, she has transformed almost every aspect of her life. She has quit smoking, run a marathon, and been promoted at work. The patterns neurologists discover, have fundamentally changed.",
  "price": 163,
  "rating": 4.5,
  "sellerId": "44925a0d-ead9-45a6-bd9b-7d636b119be5",
  "id": "639b21216d5466e941ced096"
}
